sarzaminget/__init__.py
sarzaminget/__main__.py
sarzaminget-1.1.0.dist-info/METADATA
sarzaminget-1.1.0.dist-info/WHEEL
sarzaminget-1.1.0.dist-info/RECORD
