Metadata-Version: 2.4
Name: sarzaminget
Version: 1.1.0
Author-email: NexusSfan <nexussfan@duck.com>
License-Expression: GPL-3.0-or-later
Requires-Python: >=3.10
Requires-Dist: beautifulsoup4
Requires-Dist: lxml
Requires-Dist: requests
Requires-Dist: tqdm
Requires-Dist: yt-dlp
